[
  {
    "content": "Fix PDF Polish font - register DejaVu Sans in ReportLab",
    "status": "completed"
  },
  {
    "content": "Backend: WordPress settings endpoints (admin configures WP URL + credentials)",
    "status": "completed"
  },
  {
    "content": "Backend: Publish-to-WordPress endpoint (WP REST API)",
    "status": "completed"
  },
  {
    "content": "Frontend: WordPress config in admin settings page",
    "status": "completed"
  },
  {
    "content": "Frontend: 'Opublikuj na WordPress' button in ExportPanel",
    "status": "completed"
  },
  {
    "content": "Generate downloadable WordPress plugin (PHP)",
    "status": "completed"
  },
  {
    "content": "Testing",
    "status": "completed"
  }
]